[
    {
      "_id": "6384ff2281988ce75d6dece0",
      "index": 0,
      "guid": "adcb0cef-ff38-4953-82b1-0ff808dd4c78",
      "isActive": true,
      "balance": "$1,476.84",
      "picture": "https://ychef.files.bbci.co.uk/976x549/p04tx3m6.jpg",
      "age": 26,
      "name": "Isabelle Burch",
      "gender": "female",
      "company": "PRIMORDIA"
    },
    {
      "_id": "6384ff22da9ed93b961e8617",
      "index": 1,
      "guid": "8097e796-973a-489b-8aea-1019b33b3b6f",
      "isActive": false,
      "balance": "$2,277.88",
      "picture": "https://encrypted-tbn0.gstatic.com/images?q=tbn:ANd9GcTJ_OEpkm1-d_ZUTsZpSRhbnQjVxCo2yH6Ir4I6T-Y5AxRlnHsYLmSsRwiWEJJAkMwxgQw&usqp=CAU",
      "age": 34,
      "name": "Saunders Stark",
      "gender": "male",
      "company": "HARMONEY"
    },
    {
      "_id": "6384ff22b43e982a5a7c230f",
      "index": 2,
      "guid": "2df4c2bd-3a4f-4e87-97aa-ac5fc7bd064e",
      "isActive": true,
      "balance": "$3,783.93",
      "picture": "https://static01.nyt.com/images/2021/01/26/well/well-foods-microbiome/well-foods-microbiome-superJumbo.jpg",
      "age": 22,
      "name": "Collins Sampson",
      "gender": "male",
      "company": "QUAILCOM"
    },
    {
      "_id": "6384ff22500140508b67c3f4",
      "index": 3,
      "guid": "066374a0-3267-4b95-b984-06ecdb12ca99",
      "isActive": false,
      "balance": "$1,089.14",
      "picture": "https://encrypted-tbn0.gstatic.com/images?q=tbn:ANd9GcSWDLZ1fL_TIud_NTyYg9qcnrgMrvz4xChbIqcjLU2VJBn0nk9Us3FWl1z0b_GAqlBBj0A&usqp=CAU",
      "age": 36,
      "name": "Dona Huff",
      "gender": "female",
      "company": "SUREPLEX"
    },
    {
      "_id": "6384ff225ab235cc9bb66e33",
      "index": 4,
      "guid": "9c40db69-7365-4fab-88ae-c1ba7d01be67",
      "isActive": false,
      "balance": "$3,931.56",
      "picture": "https://encrypted-tbn0.gstatic.com/images?q=tbn:ANd9GcRHPBKGd_FMXSxvzzxdxGaG4HYsN6wNGTtBUxghU0JCK5h9ED1DfLkAnb0CKpzieRspSB0&usqp=CAU",
      "age": 21,
      "name": "Rosie Franks",
      "gender": "female",
      "company": "INQUALA"
    },
    {
      "_id": "6384ff22be1429c03e7ce8f5",
      "index": 5,
      "guid": "f4d23cf2-db75-4189-9ef8-5821210347b9",
      "isActive": true,
      "balance": "$1,631.93",
      "picture": "https://blogs.biomedcentral.com/on-medicine/wp-content/uploads/sites/6/2019/09/iStock-1131794876.t5d482e40.m800.xtDADj9SvTVFjzuNeGuNUUGY4tm5d6UGU5tkKM0s3iPk-620x342.jpg",
      "age": 40,
      "name": "Christa Kirkland",
      "gender": "female",
      "company": "ZIDOX"
    }
  ]